Workbook

Sheet Instrucciones
A1: Plantilla BOM · Bill of Materials
A2: Taller Integrado · Diseño + Ingeniería · ExploraTec UDD
A4: Regla de oro | B4: Otra persona debería entender qué comprar sin tener que preguntarle al diseñador.
A6: Leyenda
A7: Celda blanca | B7: Se completa a mano. Las columnas Subsistema, Unidad, Disponibilidad y Estado tienen lista desplegable.
A8: Celda gris | B8: Se calcula sola (fórmula). No editar.
A9: Celda amarilla | B9: Dato de encabezado del proyecto (nombre, equipo, versión, fecha).
A10: Texto azul | B10: Valor ingresado a mano que alimenta cálculos (cantidades y precios).
A12: Columnas del BOM
A13: ID | B13: Código único por ítem. Prefijo por subsistema: E electrónica · M mecánica · F fabricación · T terminaciones · A ensamblaje · O otros (E01, E02, M01…). No se reutiliza un ID eliminado.
A14: Subsistema | B14: Agrupa el BOM más allá de la electrónica y ayuda a repartir responsabilidades.
A15: Función (arquitectura) | B15: Qué función de la arquitectura cumple el ítem. Debe escribirse igual que en la hoja Trazabilidad.
A16: Componente | B16: Qué es, en términos genéricos (sensor ambiental, fuente, tornillo).
A17: Especificación | B17: Lo necesario para comprar sin preguntar: modelo, voltaje, medidas, material, norma (AHT10 I²C; M3 × 12 mm).
A18: Fabricante / MPN | B18: Marca y código de parte del fabricante, cuando exista.
A19: Cant. / Unidad | B19: Cantidad por prototipo y su unidad (un., m, m²…).
A20: Proveedor / Enlace | B20: Dónde se compra y enlace a la tienda o al datasheet.
A21: $ Unit. / $ Total | B21: Precio unitario en CLP con IVA; el total se calcula solo.
A22: Disponibilidad / Alternativa | B22: ¿Existe localmente? ¿Qué lo reemplaza si no hay stock?
A23: Estado | B23: Avance de la compra: por cotizar → cotizado → comprado → recibido → instalado.
A24: Trazabilidad | B24: Se calcula sola: ✓ si la función existe en la hoja Trazabilidad; «Revisar» si no.
... A28: Datos de ejemplo | B28: Las filas precargadas usan el caso guía de la clase (estación ambiental). Los precios del ESP32, AHT10 y WS2812B son los valores referenciales de la presentación; el resto queda por cotizar. Borren las filas de ejemplo al usar la plantilla.

Sheet BOM
A1: BILL OF MATERIALS
A2: Proyecto | B2: Sistema de cortafuegos | E2: Costo total (CLP) | F2: =SUM(L9:L165) -> 210790
A3: Equipo | B3: Grupo 1 | E3: N° de ítems | F3: =COUNTA(D9:D165) -> 19
A4: Versión | B4: BOM_v01 | E4: Ítems sin precio | F4: =SUMPRODUCT((D9:D165<>"")*(K9:K165="")) -> 1
A5: Fecha | B5: 46294 | E5: Ítems por revisar (trazab.) | F5: =COUNTIF(P9:P165,"Revisar") -> 3
A8: ID | B8: Subsistema | C8: Función (arquitectura) | D8: Componente | E8: Especificación | F8: Fabricante / MPN | G8: Cant. | H8: Unidad | I8: Proveedor | J8: Enlace (tienda o datasheet) | K8: $ Unit. (CLP) | L8: $ Total (CLP) | M8: Disponibilidad | N8: Alternativa / reemplazo | O8: Estado | P8: Trazabilidad | Q8: Notas
A9: E01 | B9: Electronica | C9: Procesar datos de sensores y transmitirlos al sistema de visualización | D9: Microcontrolador | E9: ESP32-S3 DevKitC-1 N8, 3,3 V, Wi-Fi/BLE, I²C/SPI/UART | F9: Espressif / ESP32-S3-DevKitC-1-N8 | G9: 1 | H9: un. | I9: MCI Electronics | J9: ESP32-S3 DevKitC-1 – MCI | K9: 12990 | L9: 12990 | M9: Disponible online y en tienda en Santiago (MCi Electronics) | N9: ESP32-S3 DevKit genérico | O9: Por cotizar | Q9: Controlador principal
A10: E02 | B10: Electronica | C10: Capturar imágenes visibles del entorno | D10: Cámara RGB | E10: ESP32-CAM con OV2640, 2 MP, alimentación 5 V | F10: Ai-Thinker / ESP32-CAM + OV2640 | G10: 1 | H10: un. | I10: MCI Electronics | J10: https://mcielectronics.cl/shop/product/placa-esp32-cam-wifi-bluetooth/?srsltid=AU7gw4W94rWs7PVjKlXexxpIX6bHJRS4si8Lf07ZchWQecdAf2qFsncD | K10: 14990 | L10: 14990 | M10: Disponible localmente | N10: Webcam USB | O10: Por cotizar | Q10: Puede operar como módulo independiente
A11: E04 | B11: Electronica | C11: Medir temperatura y humedad ambiental | D11: Sensor ambiental | E11: BME280, I²C/SPI, temperatura, humedad y presión | F11: Bosch Sensortec / BME280 | G11: 1 | H11: un. | I11: Mercado Libre Chile | J11: https://www.mercadolibre.cl/sensor-presion-barometrica-i2c-spi-bmp280-arduino--max-/up/MLCU17972228?pdp_filters=item_id%3AMLC443971779&from=gshop&matt_tool=48536676&matt_word=&matt_source=google&matt_campaign_id=22116391875&matt_ad_group_id=172632289919&matt_match_type=&matt_network=g&matt_device=c&matt_creative=729648297992&matt_keyword=&matt_ad_position=&matt_ad_type=pla&matt_merchant_id=350136068&matt_product_id=MLCU17972228&matt_product_partition_id=2496335524795&matt_target_id=aud-2489109179440:pla-2496335524795&cq_src=google_ads&cq_cmp=22116391875&cq_net=g&cq_plt=gp&cq_med=pla&gad_source=1&gad_campaignid=22116391875&gbraid=0AAAAADxxu6qqIdqh2NcH-GVRYtNheTMep&gclid=CjwKCAjww-3VBhAcEiwAwUUIuzWOH0byKon5thHTzPOURAHwCikcJoQtHonGeCUmgUcoDFQAyZAM4RoC6YMQAvD_BwE | K11: 3000 | L11: 3000 | M11: Disponible según stock local | N11: AHT10 o DHT22 | O11: Por cotizar | Q11: Un sensor resuelve T° y HR
A12: E05 | B12: Electronica | C12: Medir temperatura del suelo | D12: Sensor de temperatura | E12: DS18B20 impermeable, sonda 1 m, interfaz 1-Wire | F12: Analog Devices / DS18B20 | G12: 1 | H12: un. | I12: MCI Electronics | J12: https://mcielectronics.cl/shop/product/sensor-de-temperatura-ds18b20-resistente-al-agua-1m-25764/?srsltid=AU7gw4WZwf1L0XQYcBdMOXL9X34Z6bQr82x6fxE8vaW994y4tPfGMTAa | K12: 2690 | L12: 2690 | M12: Disponible localmente | N12: Sonda NTC impermeable | O12: Por cotizar | Q12: Se instala enterrado
A13: E06 | B13: Electronica | C13: Medir humedad del suelo | D13: Sensor de humedad | E13: Sensor capacitivo V1.2, 3,3–5 V, salida analógica | F13: Genérico / Capacitive Soil Moisture Sensor V1.2 | G13: 1 | H13: un. | I13: MCI Electronics | J13: https://mcielectronics.cl/shop/product/modulo-detector-de-humedad-del-suelo-30176/ | K13: 5000 | L13: 5000 | M13: Habitualmente disponible | N13: Sensor capacitivo equivalente | O13: Por cotizar | Q13: Evitar sensor resistivo por corrosión
A14: E07 | B14: Electronica | C14: Indicar visualmente el estado del nodo | D14: Indicador luminoso | E14: LED RGB o módulo semáforo, 3 estados | F14: Genérico | G14: 1 | H14: un. | I14: MCI Electronics | J14: https://mcielectronics.cl/shop/product/pack-de-10-leds-blancos-de-alto-brillo-30077/?srsltid=AU7gw4UG6Y7tLSx50vH7om5Qx5yNkp2LlGM8TVFsr-ITvAUltLMXSfyU | K14: 1890 | L14: 1890 | M14: Alta disponibilidad | N14: 3 LED individuales | O14: Por cotizar | Q14: Verde / amarillo / rojo
A15: E08 | B15: Electronica | C15: Emitir una alerta sonora ante una condición crítica | D15: Buzzer | E15: Buzzer activo, 5 V | F15: Genérico | G15: 1 | H15: un. | I15: MCI Electronics | J15: https://mcielectronics.cl/shop/product/buzzer-para-montar-en-pcb-12mm-2048khz-9738/ | K15: 1490 | L15: 1490 | M15: Alta disponibilidad | N15: Buzzer pasivo | O15: Por cotizar | Q15: Activación comandada por ESP32
A16: E09 | B16: Electronica | C16: Conectar los sensores al controlador | D16: Cables jumper | E16: Dupont M-M / M-H / H-H, paso 2,54 mm | F16: Genérico | G16: 1 | H16: set | I16: MCI Electronics | J16: https://mcielectronics.cl/shop/product/cable-dupont-macho-hembra-20cm-pack-40-unidades-2/ | K16: 2000 | L16: 2000 | M16: Alta disponibilidad | N16: Cable AWG22 | O16: Por cotizar | Q16: Para prototipo desmontable
A17: E10 | B17: Electronica | C17: Montar temporalmente sensores y circuitos | D17: Protoboard | E17: 400–830 puntos, paso 2,54 mm | F17: Genérico | G17: 1 | H17: un. | I17: MCI Electronics | J17: https://mcielectronics.cl/shop/product/protoboard-de-tamano-completo-830pts-mb-102-23380/ | K17: 2500 | L17: 2500 | M17: Disponible | N17: PCB perforada | O17: Por cotizar | Q17: Facilita pruebas
A18: E11 | B18: Electronica | C18: Medir dirección del viento | D18: Sensor Dirección Viento | E18: YS-WDD01 | F18: Genérico | G18: 1 | H18: un. | I18: Mechatronics | J18: https://www.mechatronicstore.cl/sensor-direccion-viento-360-veleta/?srsltid=AU7gw4VERf0fJ80dP5bom8dB6vqQ-a4WRnv8fLOSzQEFsnf_RLw1xB3R | K18: 30000 | L18: 30000 | M18: Disponible
A19: E12 | B19: Electronica | C19: velocidad del viento | D19: Sensor De Velocidad Del Viento | E19: 0-70 M/s, Señal Ambiental | F19: Genérico | G19: 1 | H19: un. | I19: Mercado Libre Chile | J19: https://www.google.com/aclk?sa=L&ai=DChsSEwi7-N2QkJSXAxUeVEgAHU5iBIAYACICCAEQDRoCY2U&co=1&ase=2&gclid=CjwKCAjww-3VBhAcEiwAwUUIuwE_9VzbsAymNDAg2Jc4snpwCStCJiEUL4kaUHKhVu6phdPkX23d-RoCI6EQAvD_BwE&ei=Bty7aufILLLK1sQPltqoiQo&cid=CAAS3QHkaOEKJtP8u2lJaCZrZmmceXICH0vJECezFu8i8g9xFsh23cvhY0gsWR1Q6HlkeM9ZnzGCKKgTZNjVSNGy9p1mccgxBA2Xn1WPiw-T_TSjXBzqPqRcqHEky7U85HzwU_4QgKuzIiLjS0TvUcJFp_l-b8_HZ6lmJNsbLsKPBZt1fnxfQQurz8DLQ9z1G9GI4nh3Fso5W2R7JlAck_wLJLKfDd9xaCHzttCj8f3mQpebKZuaz-fTyunaSBivujuxshiEa3H86Qm5FGp1rldA_9kLudNn0Mn6DZiNBcQNZQ&cce=2&category=acrcp_v1_32&sig=AOD64_3l6Gdx43OggWBgPIcGt9h1wacQQw&ctype=5&q=&nis=4&sqi=2&ved=2ahUKEwjn49aQkJSXAxUypZUCHRYtKqEQ5bgDKAB6BAgNEBc&adurl= | K19: 14000 | L19: 14000 | M19: Disponible | O19: Por cotizar | Q19: Gira físicamente pero no entrega lectura
C20: Medir acidez/alcalinidad del suelo | D20: Módulo Sensor de PH | E20: sensor PH 0-14 con sonda de electrodo BNC | F20: Genérico | G20: 1 | H20: un. | I20: Mechatronics | J20: https://www.mechatronicstore.cl/kit-modulo-sensor-de-ph-sonda-de-electrodo-bnc-arduino/?srsltid=AU7gw4V7sdBYMTnshKrxj1kJ7x_0IbzAiwGk_GrUxE0CWf_J_SlPjB2JXl4 | K20: 24900 | L20: 24900 | M20: Disponible
A21: E14 | B21: Electronica | C21: Medir nitrógeno, fósforo y potasio | D21: Sensor NPK | F21: Genérico | G21: 1 | H21: un. | I21: Mechatronics | J21: https://www.mechatronicstore.cl/sensor-de-suelo-npk-sn-3002/?srsltid=AU7gw4VoVMq4J2i0b4bbg58jUWbnq3R7MRkboDW-RPL8YMrZP7q7DUri | K21: 62990 | L21: 62990 | M21: Disponible | O21: Por cotizar
A22: S01 | B22: Estructura | C22: Construir la base física de la maqueta | D22: MDF | E22: MDF natural, 3 mm, 400 × 400 mm | F22: Masisa / cód. tienda 39856X | G22: 1 | H22: placa | I22: Sodimac | J22: MDF 3 mm 40×40 – Sodimac | K22: 1390 | L22: 1390 | M22: Disponible; la consulta muestra stock en RM | N22: MDF 5,5 mm | O22: Por cotizar | Q22: Base principal de la maqueta
A23: S02 | B23: Estructura | C23: Construcción del cortafuego | D23: PLA | E23: Filamento PLA+ Blanco 1kg Elegoo | F23: Diseño propio | G23: 1 | H23: un. | I23: Impresión 3D UDD | J23: TodoToner | K23: 2500 | L23: 12790 | M23: Disponible | N23: TodoToner | O23: Por cotizar | Q23: Infraestructura que va sobre la base principal de la maqueta
B24: Ensamblaje | C24: Union de la base fisica de la maqueta | D24: Agorex 90 cc | E24: Adhesivo transparente | F24: Agorex | G24: 1 | H24: un. | I24: Unimarc | J24: https://www.unimarc.cl/product/adhesivo-transparente-agorex-90-cc?srsltid=AU7gw4Xv2WDgQ2t3T9DouW4i4AX8SKQCJzIlV9iFcBjj-bllzw7CG3OAbLs | K24: 6790 | L24: =IF(OR(G24="",K24=""),"",G24*K24) -> 6790 | M24: Disponible en Chile | O24: Por cotizar | P24: =IF(C25="","",IF(COUNTIF(Trazabilidad!$A$5:$A$60,C25)>0,"✓","Revisar")) -> Revisar | Q24: Ensamblaje de la maqueta
B25: Ensamblaje | C25: Union de piezas de la maqueta | D25: Silicona caliente | L25: =IF(OR(G25="",K25=""),"",G25*K25) | O25: Por cotizar | P25: =IF(#REF!="","",IF(COUNTIF(Trazabilidad!$A$5:$A$60,#REF!)>0,"✓","Revisar")) -> #REF!
A26: T01 | B26: Terminaciones | C26: Recubrimiento para aplicaciones electricas | D26: Cinta aislante | E26: Aplicaciones eléctricas | F26: Tesa | G26: 1 | H26: un. | I26: Easy | J26: https://www.easy.cl/cinta-aislante-18-mm-5-m-tesa-529109/p?idsku=6205&gad_source=4&gad_campaignid=24048792210&gbraid=0AAAAAD6SqDmoWtcLn1ocfZbpmSEHbgXWX&gclid=CjwKCAjww-3VBhAcEiwAwUUIu6eh6fpbJ3r0fkw53JyRF1vtsNJ7Rz_vnb95Tb1xfDKajWjxo94gyxoCTo0QAvD_BwE | K26: 890 | L26: =IF(OR(G26="",K26=""),"",G26*K26) -> 890 | M26: Disponible en Chile | O26: Por cotizar | P26: =IF(C26="","",IF(COUNTIF(Trazabilidad!$A$5:$A$60,C26)>0,"✓","Revisar")) -> Revisar
A27: T02 | B27: Terminaciones | C27: Terminaciones de pintura para detalles | D27: Set de pinturas acrilicas | E27: Set Acrílicos 12 Colores 12ml. Artel | F27: Artel | G27: 1 | H27: un. | I27: Eltit | J27: https://super.eltit.cl/products/artel-acrilicos-12-un | K27: 5990 | L27: =IF(OR(G27="",K27=""),"",G27*K27) -> 5990 | M27: Disponible en Chile | O27: Por cotizar | P27: =IF(#REF!="","",IF(COUNTIF(Trazabilidad!$A$5:$A$60,#REF!)>0,"✓","Revisar")) -> #REF!
J28: https://lamaqueteria.cl/producto/figuras-a-escala-1200-pack-30-uds/?srsltid=AU7gw4VJNCNeWCePSWJolCeVNQ6rBmkB4BRIKWUPsE0UmkNZNhRYkBCzpBk | K28: 4500 | L28: 4500 | M28: Disponible en Chile | P28: =IF(C27="","",IF(COUNTIF(Trazabilidad!$A$5:$A$60,C27)>0,"✓","Revisar")) -> Revisar
L29: =IF(OR(G29="",K29=""),"",G29*K29) | P29: =IF(C29="","",IF(COUNTIF(Trazabilidad!$A$5:$A$60,C29)>0,"✓","Revisar"))
L30: =IF(OR(G30="",K30=""),"",G30*K30) | P30: =IF(C30="","",IF(COUNTIF(Trazabilidad!$A$5:$A$60,C30)>0,"✓","Revisar"))
L31: =IF(OR(G31="",K31=""),"",G31*K31) | P31: =IF(C31="","",IF(COUNTIF(Trazabilidad!$A$5:$A$60,C31)>0,"✓","Revisar"))
L32: =IF(OR(G32="",K32=""),"",G32*K32) | P32: =IF(C32="","",IF(COUNTIF(Trazabilidad!$A$5:$A$60,C32)>0,"✓","Revisar"))
L33: =IF(OR(G33="",K33=""),"",G33*K33) | P33: =IF(C33="","",IF(COUNTIF(Trazabilidad!$A$5:$A$60,C33)>0,"✓","Revisar"))
L34: =IF(OR(G34="",K34=""),"",G34*K34) | P34: =IF(C34="","",IF(COUNTIF(Trazabilidad!$A$5:$A$60,C34)>0,"✓","Revisar"))
L35: =IF(OR(G35="",K35=""),"",G35*K35) | P35: =IF(C35="","",IF(COUNTIF(Trazabilidad!$A$5:$A$60,C35)>0,"✓","Revisar"))
L36: =IF(OR(G36="",K36=""),"",G36*K36) | P36: =IF(C36="","",IF(COUNTIF(Trazabilidad!$A$5:$A$60,C36)>0,"✓","Revisar"))
L37: =IF(OR(G37="",K37=""),"",G37*K37) | P37: =IF(C37="","",IF(COUNTIF(Trazabilidad!$A$5:$A$60,C37)>0,"✓","Revisar"))
L38: =IF(OR(G38="",K38=""),"",G38*K38) | P38: =IF(C38="","",IF(COUNTIF(Trazabilidad!$A$5:$A$60,C38)>0,"✓","Revisar"))
L39: =IF(OR(G39="",K39=""),"",G39*K39) | P39: =IF(C39="","",IF(COUNTIF(Trazabilidad!$A$5:$A$60,C39)>0,"✓","Revisar"))
L40: =IF(OR(G40="",K40=""),"",G40*K40) | P40: =IF(C40="","",IF(COUNTIF(Trazabilidad!$A$5:$A$60,C40)>0,"✓","Revisar"))
... L165: =IF(OR(G165="",K165=""),"",G165*K165) | P165: =IF(C165="","",IF(COUNTIF(Trazabilidad!$A$5:$A$60,C165)>0,"✓","Revisar"))

Sheet Trazabilidad
A1: Trazabilidad arquitectura ↔ BOM
A2: Liste aquí las funciones de su arquitectura. Cada función física debería tener al menos un ítem en el BOM.
A4: Función | B4: Capa | C4: Descripción | D4: N° ítems en BOM | E4: Costo asociado (CLP) | F4: Estado
A5: Medir temperatura y humedad | B5: 3 Dispositivos | C5: Leer variables del entorno. | D5: =IF(A5="","",COUNTIF(BOM!$C$9:$C$165,A5)) -> 0 | E5: =IF(A5="","",SUMIF(BOM!$C$9:$C$165,A5,BOM!$L$9:$L$165)) -> 0 | F5: =IF(A5="","",IF(D5=0,IF(B5="6 Información","Servicio / software (sin BOM físico)","Sin componente → falta en BOM"),"OK")) -> Sin componente → falta en BOM
A6: Medir luz | B6: 3 Dispositivos | C6: Leer la luminosidad del parque. | D6: =IF(A6="","",COUNTIF(BOM!$C$9:$C$165,A6)) -> 0 | E6: =IF(A6="","",SUMIF(BOM!$C$9:$C$165,A6,BOM!$L$9:$L$165)) -> 0 | F6: =IF(A6="","",IF(D6=0,IF(B6="6 Información","Servicio / software (sin BOM físico)","Sin componente → falta en BOM"),"OK")) -> Sin componente → falta en BOM
A7: Procesar y comunicar | B7: 5 Procesamiento | C7: Leer sensores, decidir y enviar datos por Wi-Fi. | D7: =IF(A7="","",COUNTIF(BOM!$C$9:$C$165,A7)) -> 0 | E7: =IF(A7="","",SUMIF(BOM!$C$9:$C$165,A7,BOM!$L$9:$L$165)) -> 0 | F7: =IF(A7="","",IF(D7=0,IF(B7="6 Información","Servicio / software (sin BOM físico)","Sin componente → falta en BOM"),"OK")) -> Sin componente → falta en BOM
A8: Mostrar estado local | B8: 2 Interacción | C8: Feedback visual al visitante, aun sin internet. | D8: =IF(A8="","",COUNTIF(BOM!$C$9:$C$165,A8)) -> 0 | E8: =IF(A8="","",SUMIF(BOM!$C$9:$C$165,A8,BOM!$L$9:$L$165)) -> 0 | F8: =IF(A8="","",IF(D8=0,IF(B8="6 Información","Servicio / software (sin BOM físico)","Sin componente → falta en BOM"),"OK")) -> Sin componente → falta en BOM
A9: Alimentar el sistema | B9: 3 Dispositivos | C9: Entregar 5 V estables al ESP32 y la tira LED. | D9: =IF(A9="","",COUNTIF(BOM!$C$9:$C$165,A9)) -> 0 | E9: =IF(A9="","",SUMIF(BOM!$C$9:$C$165,A9,BOM!$L$9:$L$165)) -> 0 | F9: =IF(A9="","",IF(D9=0,IF(B9="6 Información","Servicio / software (sin BOM físico)","Sin componente → falta en BOM"),"OK")) -> Sin componente → falta en BOM
A10: Conectar componentes | B10: 3 Dispositivos | C10: Cableado y conexiones entre partes. | D10: =IF(A10="","",COUNTIF(BOM!$C$9:$C$165,A10)) -> 0 | E10: =IF(A10="","",SUMIF(BOM!$C$9:$C$165,A10,BOM!$L$9:$L$165)) -> 0 | F10: =IF(A10="","",IF(D10=0,IF(B10="6 Información","Servicio / software (sin BOM físico)","Sin componente → falta en BOM"),"OK")) -> Sin componente → falta en BOM
A11: Sostener y proteger el dispositivo | B11: Estructura física | C11: Estructura y carcasa frente a lluvia y sol. | D11: =IF(A11="","",COUNTIF(BOM!$C$9:$C$165,A11)) -> 0 | E11: =IF(A11="","",SUMIF(BOM!$C$9:$C$165,A11,BOM!$L$9:$L$165)) -> 0 | F11: =IF(A11="","",IF(D11=0,IF(B11="6 Información","Servicio / software (sin BOM físico)","Sin componente → falta en BOM"),"OK")) -> Sin componente → falta en BOM
A12: Fijar al lugar | B12: Estructura física | C12: Montaje en el parque (poste, muro, base). | D12: =IF(A12="","",COUNTIF(BOM!$C$9:$C$165,A12)) -> 0 | E12: =IF(A12="","",SUMIF(BOM!$C$9:$C$165,A12,BOM!$L$9:$L$165)) -> 0 | F12: =IF(A12="","",IF(D12=0,IF(B12="6 Información","Servicio / software (sin BOM físico)","Sin componente → falta en BOM"),"OK")) -> Sin componente → falta en BOM
A13: Registrar historial | B13: 6 Información | C13: Base de datos en el servidor. | D13: =IF(A13="","",COUNTIF(BOM!$C$9:$C$165,A13)) -> 0 | E13: =IF(A13="","",SUMIF(BOM!$C$9:$C$165,A13,BOM!$L$9:$L$165)) -> 0 | F13: =IF(A13="","",IF(D13=0,IF(B13="6 Información","Servicio / software (sin BOM físico)","Sin componente → falta en BOM"),"OK")) -> Servicio / software (sin BOM físico)
A14: FIN EJEMPLO | B14: FIN EJEMPLO | C14: FIN EJEMPLO | D14: FIN EJEMPLO | E14: FIN EJEMPLO
A15: Medir temperatura y humedad ambiental | B15: 3 Dispositivos | C15: Medir temperatura y humedad del ambiente mediante el sensor BME280. | D15: 1 | E15: =BOM!K11 -> 3000 | F15: =IF(A15="","",IF(D15=0,IF(B15="6 Información","Servicio / software (sin BOM físico)","Sin componente → falta en BOM"),"OK")) -> OK
A16: Medir humedad del suelo | B16: 3 Dispositivos | C16: Medir el nivel de humedad presente en el suelo mediante un sensor capacitivo. | D16: 1 | E16: Pendiente | F16: =IF(A16="","",IF(D16=0,IF(B16="6 Información","Servicio / software (sin BOM físico)","Sin componente → falta en BOM"),"OK")) -> OK
A17: Medir temperatura del suelo | B17: 3 Dispositivos | C17: Medir la temperatura del suelo mediante el sensor DS18B20 impermeable. | D17: =IF(A17="","",COUNTIF(BOM!$C$9:$C$165,A17)) -> 1 | E17: Pendiente | F17: =IF(A17="","",IF(D17=0,IF(B17="6 Información","Servicio / software (sin BOM físico)","Sin componente → falta en BOM"),"OK")) -> OK
A18: Detectar temperatura / focos calientes | B18: 3 Dispositivos | C18: Detectar temperatura y posibles focos de calor mediante el sensor térmico MLX90614. | D18: 1 | E18: Pendiente | F18: =IF(A18="","",IF(D18=0,IF(B18="6 Información","Servicio / software (sin BOM físico)","Sin componente → falta en BOM"),"OK")) -> OK
A19: Capturar imagen del entorno | B19: 3 Dispositivos | C19: Capturar imágenes del entorno mediante la cámara RGB ESP32-CAM. | D19: 1 | E19: Pendiente | F19: =IF(A19="","",IF(D19=0,IF(B19="6 Información","Servicio / software (sin BOM físico)","Sin componente → falta en BOM"),"OK")) -> OK
A20: Medir condiciones nutricionales del suelo | B20: 3 Dispositivos | C20: Representar la medición de nutrientes NPK presentes en el suelo. | D20: 1 | E20: Pendiente | F20: =IF(A20="","",IF(D20=0,IF(B20="6 Información","Servicio / software (sin BOM físico)","Sin componente → falta en BOM"),"OK")) -> OK
A21: Medir pH del suelo | B21: 3 Dispositivos | C21: Representar la medición del nivel de pH del suelo. | D21: 1 | E21: Pendiente | F21: =IF(A21="","",IF(D21=0,IF(B21="6 Información","Servicio / software (sin BOM físico)","Sin componente → falta en BOM"),"OK")) -> OK
A22: Medir conductividad del suelo | B22: 3 Dispositivos | C22: Representar la medición de conductividad eléctrica del suelo. | D22: 1 | E22: Pendiente | F22: =IF(A22="","",IF(D22=0,IF(B22="6 Información","Servicio / software (sin BOM físico)","Sin componente → falta en BOM"),"OK")) -> OK
A23: Medir velocidad del viento | B23: 3 Dispositivos | C23: Medir y representar la velocidad del viento mediante un anemómetro. | D23: 1 | E23: Pendiente | F23: =IF(A23="","",IF(D23=0,IF(B23="6 Información","Servicio / software (sin BOM físico)","Sin componente → falta en BOM"),"OK")) -> OK
A24: Medir dirección del viento | B24: 3 Dispositivos | C24: Medir y representar la dirección del viento mediante una veleta. | D24: 1 | E24: Pendiente | F24: =IF(A24="","",IF(D24=0,IF(B24="6 Información","Servicio / software (sin BOM físico)","Sin componente → falta en BOM"),"OK")) -> OK
A25: Determinar ubicación | B25: 3 Dispositivos | C25: Representar la ubicación del sistema mediante un módulo GPS. | D25: 1 | E25: Pendiente | F25: =IF(A25="","",IF(D25=0,IF(B25="6 Información","Servicio / software (sin BOM físico)","Sin componente → falta en BOM"),"OK")) -> OK
A26: Procesar y comunicar datos | B26: 5 Procesamiento | C26: Recibir las mediciones de los sensores, procesarlas y transmitir los datos mediante el ESP32-S3 y conexión Wi-Fi. | D26: 1 | E26: Pendiente | F26: =IF(A26="","",IF(D26=0,IF(B26="6 Información","Servicio / software (sin BOM físico)","Sin componente → falta en BOM"),"OK")) -> OK
A27: Mostrar estado local | B27: 2 Interacción | C27: Entregar retroalimentación visual y sonora según las mediciones y estados detectados. | D27: 2 | E27: Pendiente | F27: =IF(#REF!="","",IF(D27=0,IF(B27="6 Información","Servicio / software (sin BOM físico)","Sin componente → falta en BOM"),"OK")) -> #REF!
A28: Iluminar el entorno | B28: 2 Interacción | C28: Proporcionar iluminación mediante una tira o sistema LED RGB / NeoPixel. | D28: 1 | E28: Pendiente | F28: =IF(A27="","",IF(D28=0,IF(B28="6 Información","Servicio / software (sin BOM físico)","Sin componente → falta en BOM"),"OK")) -> OK
A29: Activar alerta visual | B29: 2 Interacción | C29: Activar una señal visual mediante LED RGB o torre de alerta según los datos registrados. | D29: 1 | E29: Pendiente | F29: =IF(A29="","",IF(D29=0,IF(B29="6 Información","Servicio / software (sin BOM físico)","Sin componente → falta en BOM"),"OK")) -> OK
A30: Activar alerta sonora | B30: 2 Interacción | C30: Emitir una alerta sonora mediante un buzzer cuando se detecte una condición determinada. | D30: 1 | E30: Pendiente | F30: =IF(A30="","",IF(D30=0,IF(B30="6 Información","Servicio / software (sin BOM físico)","Sin componente → falta en BOM"),"OK")) -> OK
A31: Representar datos en dashboard | B31: 6 Información | C31: Enviar y visualizar los datos de sensores mediante un dashboard conectado por Wi-Fi. | D31: 1 | E31: Pendiente | F31: =IF(A31="","",IF(D31=0,IF(B31="6 Información","Servicio / software (sin BOM físico)","Sin componente → falta en BOM"),"OK")) -> OK
A32: Proteger los componentes electrónicos | B32: Estructura física | C32: Proteger sensores y componentes electrónicos mediante la carcasa del sistema IoT/NB. | D32: 1 | E32: Pendiente | F32: =IF(A32="","",IF(D32=0,IF(B32="6 Información","Servicio / software (sin BOM físico)","Sin componente → falta en BOM"),"OK")) -> OK
A33: Sostener el sistema | B33: Estructura física | C33: Sostener físicamente los sensores, componentes y elementos de interacción mediante la torre principal. | D33: 1 | E33: Pendiente | F33: =IF(A33="","",IF(D33=0,IF(B33="6 Información","Servicio / software (sin BOM físico)","Sin componente → falta en BOM"),"OK")) -> OK
A34: Fijar el sistema al terreno | B34: Estructura física | C34: Permitir el montaje y estabilidad de la torre y sus componentes sobre el terreno. | D34: 1 | E34: Pendiente | F34: =IF(A34="","",IF(D34=0,IF(B34="6 Información","Servicio / software (sin BOM físico)","Sin componente → falta en BOM"),"OK")) -> OK
A35: Representar el territorio de interfaz | B35: Estructura física | C35: Representar físicamente el territorio urbano-forestal donde se implementa el sistema. | D35: 1 | E35: Pendiente | F35: =IF(A35="","",IF(D35=0,IF(B35="6 Información","Servicio / software (sin BOM físico)","Sin componente → falta en BOM"),"OK")) -> OK

Sheet Resumen
A1: Resumen por subsistema
A3: Subsistema | B3: N° ítems | C3: Costo (CLP) | D3: % del total | E3: Ítems sin precio
A4: Electrónica | B4: 10 | C4: =BOM!L9+BOM!L10+BOM!L11+BOM!L12+BOM!L13+BOM!L14+BOM!L15+BOM!L16+BOM!L17 -> 46550 | D4: =IF($C$10=0,0,C4/$C$10) -> 0.62567204 | E4: =COUNTIFS(BOM!$B$9:$B$165,A4,BOM!$K$9:$K$165,"") -> 0
A5: Mecánica / estructura | B5: 2 | C5: =BOM!L22+BOM!L23 -> 14180 | D5: =IF($C$10=0,0,C5/$C$10) -> 0.1905914 | E5: =COUNTIFS(BOM!$B$9:$B$165,A5,BOM!$K$9:$K$165,"") -> 0
A6: Fabricación | B6: 2 | C6: =SUMIF(BOM!$B$9:$B$165,A6,BOM!$L$9:$L$165) -> 0 | D6: =IF($C$10=0,0,C6/$C$10) -> 0 | E6: =COUNTIFS(BOM!$B$9:$B$165,A6,BOM!$K$9:$K$165,"") -> 0
A7: Terminaciones | B7: =COUNTIF(BOM!$B$9:$B$165,A7) -> 2 | C7: =SUMIF(BOM!$B$9:$B$165,A7,BOM!$L$9:$L$165) -> 6880 | D7: =IF($C$10=0,0,C7/$C$10) -> 0.092473118 | E7: =COUNTIFS(BOM!$B$9:$B$165,A7,BOM!$K$9:$K$165,"") -> 0
A8: Ensamblaje | B8: =COUNTIF(BOM!$B$9:$B$165,A8) -> 2 | C8: =SUMIF(BOM!$B$9:$B$165,A8,BOM!$L$9:$L$165) -> 6790 | D8: =IF($C$10=0,0,C8/$C$10) -> 0.091263441 | E8: =COUNTIFS(BOM!$B$9:$B$165,A8,BOM!$K$9:$K$165,"") -> 1
A9: Según el proyecto | B9: =COUNTIF(BOM!$B$9:$B$165,A9) -> 0 | C9: 0 | D9: =IF($C$10=0,0,C9/$C$10) -> 0 | E9: =COUNTIFS(BOM!$B$9:$B$165,A9,BOM!$K$9:$K$165,"") -> 0
A10: Total | B10: =SUM(B4:B9) -> 18 | C10: =SUM(C4:C9) -> 74400 | D10: =SUM(D4:D9) -> 1 | E10: =SUM(E4:E9) -> 1
A12: El costo solo considera ítems con precio. Revise «Ítems sin precio» antes de presentar un presupuesto.

Sheet Historial
A1: Historial de versiones
A3: Versión | B3: Fecha | C3: Autor | D3: Qué cambió | E3: Por qué | F3: Ítems afectados (ID) | G3: Efecto en costo (CLP)
A4: BOM_v01 | B4: 46294 | C4: Grupo 1 | D4: Primera versión a partir de la arquitectura mínima viable. | E4: Traducir las funciones de la arquitectura a componentes concretos. | F4: E01–M02

Sheet Listas
A1: Subsistema | B1: Unidad | C1: Disponibilidad | D1: Estado | E1: Capa
A2: Electrónica | B2: un. | C2: Disponible en Chile | D2: Por cotizar | E2: 1 Personas / contexto
A3: Mecánica / estructura | B3: m | C3: Importación | D3: Cotizado | E3: 2 Interacción
A4: Fabricación | B4: m² | C4: Sin stock | D4: Comprado | E4: 3 Dispositivos
A5: Terminaciones | B5: cm | C5: Por verificar | D5: Recibido | E5: 4 Comunicación
A6: Ensamblaje | B6: kg | D6: Instalado | E6: 5 Procesamiento
A7: Según el proyecto | B7: g | D7: Descartado | E7: 6 Información
B8: ml | E8: 7 Servicios
B9: set | E9: Estructura física
B10: hr
